{
	"Id": "ALOUETTE2_NEPROF_TOPS",
	"Observatory": [
		"Alouette-2"
	],
	"Instrument": [
		"TOPS"
	],
	"ObservatoryGroup": [
		"Alouette"
	],
	"InstrumentType": [
		"Imaging and Remote Sensing (ITM/Earth)"
	],
	"Label": "Alouette-2 CRC Electron Density Profiles - J. E. Jackson (Communication Research Centre (CRC), Ottawa)",
	"TimeInterval": {
		"Start": "1965-12-15T09:40:15.000Z",
		"End": "1972-07-10T22:37:22.000Z"
	},
	"PiName": "J. E. Jackson",
	"PiAffiliation": "Communication Research Centre (CRC), Ottawa",
	"Notes": "http://cdaweb.gsfc.nasa.gov/misc/NotesA.html#ALOUETTE2_NEPROF_TOPS",
	"DatasetLink": [
		{
			"Title": "(shows data availability)",
			"Text": "Alouette2 full listing ",
			"Url": "http://cdaweb.gsfc.nasa.gov/ISIS_ALOUETTE_DOCS/ALOUETTE2_NEPROF_TOPS_full_listing.txt"
		}
	],
	"VariableDescription": [
		{
			"Name": "density",
			"ShortDescription": "density",
			"LongDescription": "Topside electon density in cm-3 from F peak to orbit altitude",
			"Header": "# ******************************************************* \n#  WARNING: Increase time period selected for listing. \n# ******************************************************* \n# \n#              ************************************\n#              *****    GLOBAL ATTRIBUTES    ******\n#              ************************************\n#\n#     PROJECT                         Alouette>International Satellite for Ionosphere Studies\n#                                     NSSDC>Archived Data\n#     DISCIPLINE                      Space Physics>Ionospheric Science\n#     SOURCE_NAME                     Alouette-2>International Satellite for Ionosphere Studies 2\n#     DATA_TYPE                       NEPROF>Density Profiles\n#     DESCRIPTOR                      TOPS>Topside Sounder\n#     DATA_VERSION                    1\n#     TITLE                           CRC Electron Density Profiles\n#     TEXT                            This data file contains topside electron density profiles as deduced from Alouette                     \n#     TEXT                             2 topside sounder measurements. The data processing was done in the seventies                         \n#     TEXT                             at the Communications Research Center in Ottawa, Canada This data set provides                        \n#     TEXT                             data from 1000km down in steps of irregular step size. The x- and o-traces                            \n#     TEXT                             were manually  scaled from the ionograms and the inversion algorithm of J.                            \n#                                      Jackson was used to compute the density profiles from these traces.                                   \n#     ADID_REF                        NSSD0110\n#     LOGICAL_FILE_ID                 alouette2_neprof_tops_00000000_v01\n#     LOGICAL_SOURCE                  alouette2_neprof_tops\n#     LOGICAL_SOURCE_DESCRIPTION      Alouette-2 CRC Electron Density Profiles\n#     PI_NAME                         J. E. Jackson\n#     PI_AFFILIATION                  Communication Research Centre (CRC), Ottawa\n#     MISSION_GROUP                   Alouette\n#                                     !___ITM Data including Earth Imaging and Ground-Based\n#     INSTRUMENT_TYPE                 Imaging and Remote Sensing (ITM/Earth)\n#     NSSDC_ID                        SPIO-00183\n#     LINK_TEXT                       Alouette2 full listing\n#     LINK_TITLE                      (shows data availability)\n#                                     http://cdaweb.gsfc.nasa.gov/ISIS_ALOUETTE_DOCS/ALOUETTE2_NEPROF_TOPS_full_listing.txt                  \n#\n#  \n# Key Parameter and Survey data (labels K0,K1,K2) are preliminary browse data.\n# Generated by CDAWeb on: Thu Jan 15 18:02:00 2015\n",
			"VariableInfo": "",
			"Cadence": ""
		},
		{
			"Name": "log_density",
			"ShortDescription": "log density",
			"LongDescription": "Logarithm (base 10) of topside Ne in cm-3",
			"Header": "# ******************************************************* \n#  WARNING: Increase time period selected for listing. \n# ******************************************************* \n# \n#              ************************************\n#              *****    GLOBAL ATTRIBUTES    ******\n#              ************************************\n#\n#     PROJECT                         Alouette>International Satellite for Ionosphere Studies\n#                                     NSSDC>Archived Data\n#     DISCIPLINE                      Space Physics>Ionospheric Science\n#     SOURCE_NAME                     Alouette-2>International Satellite for Ionosphere Studies 2\n#     DATA_TYPE                       NEPROF>Density Profiles\n#     DESCRIPTOR                      TOPS>Topside Sounder\n#     DATA_VERSION                    1\n#     TITLE                           CRC Electron Density Profiles\n#     TEXT                            This data file contains topside electron density profiles as deduced from Alouette                     \n#     TEXT                             2 topside sounder measurements. The data processing was done in the seventies                         \n#     TEXT                             at the Communications Research Center in Ottawa, Canada This data set provides                        \n#     TEXT                             data from 1000km down in steps of irregular step size. The x- and o-traces                            \n#     TEXT                             were manually  scaled from the ionograms and the inversion algorithm of J.                            \n#                                      Jackson was used to compute the density profiles from these traces.                                   \n#     ADID_REF                        NSSD0110\n#     LOGICAL_FILE_ID                 alouette2_neprof_tops_00000000_v01\n#     LOGICAL_SOURCE                  alouette2_neprof_tops\n#     LOGICAL_SOURCE_DESCRIPTION      Alouette-2 CRC Electron Density Profiles\n#     PI_NAME                         J. E. Jackson\n#     PI_AFFILIATION                  Communication Research Centre (CRC), Ottawa\n#     MISSION_GROUP                   Alouette\n#                                     !___ITM Data including Earth Imaging and Ground-Based\n#     INSTRUMENT_TYPE                 Imaging and Remote Sensing (ITM/Earth)\n#     NSSDC_ID                        SPIO-00183\n#     LINK_TEXT                       Alouette2 full listing\n#     LINK_TITLE                      (shows data availability)\n#                                     http://cdaweb.gsfc.nasa.gov/ISIS_ALOUETTE_DOCS/ALOUETTE2_NEPROF_TOPS_full_listing.txt                  \n#\n#  \n# Key Parameter and Survey data (labels K0,K1,K2) are preliminary browse data.\n# Generated by CDAWeb on: Thu Jan 15 18:02:00 2015\n",
			"VariableInfo": "",
			"Cadence": ""
		},
		{
			"Name": "tec",
			"ShortDescription": "",
			"LongDescription": "Total Electron Content in TECU (=1E16 m-2)",
			"Header": "# ******************************************************* \n#  WARNING: Increase time period selected for listing. \n# ******************************************************* \n# \n#              ************************************\n#              *****    GLOBAL ATTRIBUTES    ******\n#              ************************************\n#\n#     PROJECT                         Alouette>International Satellite for Ionosphere Studies\n#                                     NSSDC>Archived Data\n#     DISCIPLINE                      Space Physics>Ionospheric Science\n#     SOURCE_NAME                     Alouette-2>International Satellite for Ionosphere Studies 2\n#     DATA_TYPE                       NEPROF>Density Profiles\n#     DESCRIPTOR                      TOPS>Topside Sounder\n#     DATA_VERSION                    1\n#     TITLE                           CRC Electron Density Profiles\n#     TEXT                            This data file contains topside electron density profiles as deduced from Alouette                     \n#     TEXT                             2 topside sounder measurements. The data processing was done in the seventies                         \n#     TEXT                             at the Communications Research Center in Ottawa, Canada This data set provides                        \n#     TEXT                             data from 1000km down in steps of irregular step size. The x- and o-traces                            \n#     TEXT                             were manually  scaled from the ionograms and the inversion algorithm of J.                            \n#                                      Jackson was used to compute the density profiles from these traces.                                   \n#     ADID_REF                        NSSD0110\n#     LOGICAL_FILE_ID                 alouette2_neprof_tops_00000000_v01\n#     LOGICAL_SOURCE                  alouette2_neprof_tops\n#     LOGICAL_SOURCE_DESCRIPTION      Alouette-2 CRC Electron Density Profiles\n#     PI_NAME                         J. E. Jackson\n#     PI_AFFILIATION                  Communication Research Centre (CRC), Ottawa\n#     MISSION_GROUP                   Alouette\n#                                     !___ITM Data including Earth Imaging and Ground-Based\n#     INSTRUMENT_TYPE                 Imaging and Remote Sensing (ITM/Earth)\n#     NSSDC_ID                        SPIO-00183\n#     LINK_TEXT                       Alouette2 full listing\n#     LINK_TITLE                      (shows data availability)\n#                                     http://cdaweb.gsfc.nasa.gov/ISIS_ALOUETTE_DOCS/ALOUETTE2_NEPROF_TOPS_full_listing.txt                  \n#\n#  \n# Key Parameter and Survey data (labels K0,K1,K2) are preliminary browse data.\n# Generated by CDAWeb on: Thu Jan 15 18:02:01 2015\n",
			"VariableInfo": "",
			"Cadence": ""
		},
		{
			"Name": "tec_iri",
			"ShortDescription": "",
			"LongDescription": "IRI-95 value for TEC in TECU",
			"Header": "# ******************************************************* \n#  WARNING: Increase time period selected for listing. \n# ******************************************************* \n# \n#              ************************************\n#              *****    GLOBAL ATTRIBUTES    ******\n#              ************************************\n#\n#     PROJECT                         Alouette>International Satellite for Ionosphere Studies\n#                                     NSSDC>Archived Data\n#     DISCIPLINE                      Space Physics>Ionospheric Science\n#     SOURCE_NAME                     Alouette-2>International Satellite for Ionosphere Studies 2\n#     DATA_TYPE                       NEPROF>Density Profiles\n#     DESCRIPTOR                      TOPS>Topside Sounder\n#     DATA_VERSION                    1\n#     TITLE                           CRC Electron Density Profiles\n#     TEXT                            This data file contains topside electron density profiles as deduced from Alouette                     \n#     TEXT                             2 topside sounder measurements. The data processing was done in the seventies                         \n#     TEXT                             at the Communications Research Center in Ottawa, Canada This data set provides                        \n#     TEXT                             data from 1000km down in steps of irregular step size. The x- and o-traces                            \n#     TEXT                             were manually  scaled from the ionograms and the inversion algorithm of J.                            \n#                                      Jackson was used to compute the density profiles from these traces.                                   \n#     ADID_REF                        NSSD0110\n#     LOGICAL_FILE_ID                 alouette2_neprof_tops_00000000_v01\n#     LOGICAL_SOURCE                  alouette2_neprof_tops\n#     LOGICAL_SOURCE_DESCRIPTION      Alouette-2 CRC Electron Density Profiles\n#     PI_NAME                         J. E. Jackson\n#     PI_AFFILIATION                  Communication Research Centre (CRC), Ottawa\n#     MISSION_GROUP                   Alouette\n#                                     !___ITM Data including Earth Imaging and Ground-Based\n#     INSTRUMENT_TYPE                 Imaging and Remote Sensing (ITM/Earth)\n#     NSSDC_ID                        SPIO-00183\n#     LINK_TEXT                       Alouette2 full listing\n#     LINK_TITLE                      (shows data availability)\n#                                     http://cdaweb.gsfc.nasa.gov/ISIS_ALOUETTE_DOCS/ALOUETTE2_NEPROF_TOPS_full_listing.txt                  \n#\n#  \n# Key Parameter and Survey data (labels K0,K1,K2) are preliminary browse data.\n# Generated by CDAWeb on: Thu Jan 15 18:02:01 2015\n",
			"VariableInfo": "",
			"Cadence": ""
		},
		{
			"Name": "IRI_F2peak",
			"ShortDescription": "",
			"LongDescription": "IRI-95 value for the natural logarithm of the F2 peak density in cm-3",
			"Header": "# ******************************************************* \n#  WARNING: Increase time period selected for listing. \n# ******************************************************* \n# \n#              ************************************\n#              *****    GLOBAL ATTRIBUTES    ******\n#              ************************************\n#\n#     PROJECT                         Alouette>International Satellite for Ionosphere Studies\n#                                     NSSDC>Archived Data\n#     DISCIPLINE                      Space Physics>Ionospheric Science\n#     SOURCE_NAME                     Alouette-2>International Satellite for Ionosphere Studies 2\n#     DATA_TYPE                       NEPROF>Density Profiles\n#     DESCRIPTOR                      TOPS>Topside Sounder\n#     DATA_VERSION                    1\n#     TITLE                           CRC Electron Density Profiles\n#     TEXT                            This data file contains topside electron density profiles as deduced from Alouette                     \n#     TEXT                             2 topside sounder measurements. The data processing was done in the seventies                         \n#     TEXT                             at the Communications Research Center in Ottawa, Canada This data set provides                        \n#     TEXT                             data from 1000km down in steps of irregular step size. The x- and o-traces                            \n#     TEXT                             were manually  scaled from the ionograms and the inversion algorithm of J.                            \n#                                      Jackson was used to compute the density profiles from these traces.                                   \n#     ADID_REF                        NSSD0110\n#     LOGICAL_FILE_ID                 alouette2_neprof_tops_00000000_v01\n#     LOGICAL_SOURCE                  alouette2_neprof_tops\n#     LOGICAL_SOURCE_DESCRIPTION      Alouette-2 CRC Electron Density Profiles\n#     PI_NAME                         J. E. Jackson\n#     PI_AFFILIATION                  Communication Research Centre (CRC), Ottawa\n#     MISSION_GROUP                   Alouette\n#                                     !___ITM Data including Earth Imaging and Ground-Based\n#     INSTRUMENT_TYPE                 Imaging and Remote Sensing (ITM/Earth)\n#     NSSDC_ID                        SPIO-00183\n#     LINK_TEXT                       Alouette2 full listing\n#     LINK_TITLE                      (shows data availability)\n#                                     http://cdaweb.gsfc.nasa.gov/ISIS_ALOUETTE_DOCS/ALOUETTE2_NEPROF_TOPS_full_listing.txt                  \n#\n#  \n# Key Parameter and Survey data (labels K0,K1,K2) are preliminary browse data.\n# Generated by CDAWeb on: Thu Jan 15 18:02:02 2015\n",
			"VariableInfo": "",
			"Cadence": ""
		},
		{
			"Name": "IRI_F2peakHeight",
			"ShortDescription": "",
			"LongDescription": "IRI-95 value for F2 peak height in km",
			"Header": "# ******************************************************* \n#  WARNING: Increase time period selected for listing. \n# ******************************************************* \n# \n#              ************************************\n#              *****    GLOBAL ATTRIBUTES    ******\n#              ************************************\n#\n#     PROJECT                         Alouette>International Satellite for Ionosphere Studies\n#                                     NSSDC>Archived Data\n#     DISCIPLINE                      Space Physics>Ionospheric Science\n#     SOURCE_NAME                     Alouette-2>International Satellite for Ionosphere Studies 2\n#     DATA_TYPE                       NEPROF>Density Profiles\n#     DESCRIPTOR                      TOPS>Topside Sounder\n#     DATA_VERSION                    1\n#     TITLE                           CRC Electron Density Profiles\n#     TEXT                            This data file contains topside electron density profiles as deduced from Alouette                     \n#     TEXT                             2 topside sounder measurements. The data processing was done in the seventies                         \n#     TEXT                             at the Communications Research Center in Ottawa, Canada This data set provides                        \n#     TEXT                             data from 1000km down in steps of irregular step size. The x- and o-traces                            \n#     TEXT                             were manually  scaled from the ionograms and the inversion algorithm of J.                            \n#                                      Jackson was used to compute the density profiles from these traces.                                   \n#     ADID_REF                        NSSD0110\n#     LOGICAL_FILE_ID                 alouette2_neprof_tops_00000000_v01\n#     LOGICAL_SOURCE                  alouette2_neprof_tops\n#     LOGICAL_SOURCE_DESCRIPTION      Alouette-2 CRC Electron Density Profiles\n#     PI_NAME                         J. E. Jackson\n#     PI_AFFILIATION                  Communication Research Centre (CRC), Ottawa\n#     MISSION_GROUP                   Alouette\n#                                     !___ITM Data including Earth Imaging and Ground-Based\n#     INSTRUMENT_TYPE                 Imaging and Remote Sensing (ITM/Earth)\n#     NSSDC_ID                        SPIO-00183\n#     LINK_TEXT                       Alouette2 full listing\n#     LINK_TITLE                      (shows data availability)\n#                                     http://cdaweb.gsfc.nasa.gov/ISIS_ALOUETTE_DOCS/ALOUETTE2_NEPROF_TOPS_full_listing.txt                  \n#\n#  \n# Key Parameter and Survey data (labels K0,K1,K2) are preliminary browse data.\n# Generated by CDAWeb on: Thu Jan 15 18:02:02 2015\n",
			"VariableInfo": "",
			"Cadence": ""
		},
		{
			"Name": "numDataPoints",
			"ShortDescription": "",
			"LongDescription": "Number of data points per profile",
			"Header": "# ******************************************************* \n#  WARNING: Increase time period selected for listing. \n# ******************************************************* \n# \n#              ************************************\n#              *****    GLOBAL ATTRIBUTES    ******\n#              ************************************\n#\n#     PROJECT                         Alouette>International Satellite for Ionosphere Studies\n#                                     NSSDC>Archived Data\n#     DISCIPLINE                      Space Physics>Ionospheric Science\n#     SOURCE_NAME                     Alouette-2>International Satellite for Ionosphere Studies 2\n#     DATA_TYPE                       NEPROF>Density Profiles\n#     DESCRIPTOR                      TOPS>Topside Sounder\n#     DATA_VERSION                    1\n#     TITLE                           CRC Electron Density Profiles\n#     TEXT                            This data file contains topside electron density profiles as deduced from Alouette                     \n#     TEXT                             2 topside sounder measurements. The data processing was done in the seventies                         \n#     TEXT                             at the Communications Research Center in Ottawa, Canada This data set provides                        \n#     TEXT                             data from 1000km down in steps of irregular step size. The x- and o-traces                            \n#     TEXT                             were manually  scaled from the ionograms and the inversion algorithm of J.                            \n#                                      Jackson was used to compute the density profiles from these traces.                                   \n#     ADID_REF                        NSSD0110\n#     LOGICAL_FILE_ID                 alouette2_neprof_tops_00000000_v01\n#     LOGICAL_SOURCE                  alouette2_neprof_tops\n#     LOGICAL_SOURCE_DESCRIPTION      Alouette-2 CRC Electron Density Profiles\n#     PI_NAME                         J. E. Jackson\n#     PI_AFFILIATION                  Communication Research Centre (CRC), Ottawa\n#     MISSION_GROUP                   Alouette\n#                                     !___ITM Data including Earth Imaging and Ground-Based\n#     INSTRUMENT_TYPE                 Imaging and Remote Sensing (ITM/Earth)\n#     NSSDC_ID                        SPIO-00183\n#     LINK_TEXT                       Alouette2 full listing\n#     LINK_TITLE                      (shows data availability)\n#                                     http://cdaweb.gsfc.nasa.gov/ISIS_ALOUETTE_DOCS/ALOUETTE2_NEPROF_TOPS_full_listing.txt                  \n#\n#  \n# Key Parameter and Survey data (labels K0,K1,K2) are preliminary browse data.\n# Generated by CDAWeb on: Thu Jan 15 18:02:03 2015\n",
			"VariableInfo": "",
			"Cadence": ""
		},
		{
			"Name": "qualityIndex",
			"ShortDescription": "",
			"LongDescription": "Quality Index ( 0-best, 10-worst)",
			"Header": "# ******************************************************* \n#  WARNING: Increase time period selected for listing. \n# ******************************************************* \n# \n#              ************************************\n#              *****    GLOBAL ATTRIBUTES    ******\n#              ************************************\n#\n#     PROJECT                         Alouette>International Satellite for Ionosphere Studies\n#                                     NSSDC>Archived Data\n#     DISCIPLINE                      Space Physics>Ionospheric Science\n#     SOURCE_NAME                     Alouette-2>International Satellite for Ionosphere Studies 2\n#     DATA_TYPE                       NEPROF>Density Profiles\n#     DESCRIPTOR                      TOPS>Topside Sounder\n#     DATA_VERSION                    1\n#     TITLE                           CRC Electron Density Profiles\n#     TEXT                            This data file contains topside electron density profiles as deduced from Alouette                     \n#     TEXT                             2 topside sounder measurements. The data processing was done in the seventies                         \n#     TEXT                             at the Communications Research Center in Ottawa, Canada This data set provides                        \n#     TEXT                             data from 1000km down in steps of irregular step size. The x- and o-traces                            \n#     TEXT                             were manually  scaled from the ionograms and the inversion algorithm of J.                            \n#                                      Jackson was used to compute the density profiles from these traces.                                   \n#     ADID_REF                        NSSD0110\n#     LOGICAL_FILE_ID                 alouette2_neprof_tops_00000000_v01\n#     LOGICAL_SOURCE                  alouette2_neprof_tops\n#     LOGICAL_SOURCE_DESCRIPTION      Alouette-2 CRC Electron Density Profiles\n#     PI_NAME                         J. E. Jackson\n#     PI_AFFILIATION                  Communication Research Centre (CRC), Ottawa\n#     MISSION_GROUP                   Alouette\n#                                     !___ITM Data including Earth Imaging and Ground-Based\n#     INSTRUMENT_TYPE                 Imaging and Remote Sensing (ITM/Earth)\n#     NSSDC_ID                        SPIO-00183\n#     LINK_TEXT                       Alouette2 full listing\n#     LINK_TITLE                      (shows data availability)\n#                                     http://cdaweb.gsfc.nasa.gov/ISIS_ALOUETTE_DOCS/ALOUETTE2_NEPROF_TOPS_full_listing.txt                  \n#\n#  \n# Key Parameter and Survey data (labels K0,K1,K2) are preliminary browse data.\n# Generated by CDAWeb on: Thu Jan 15 18:02:03 2015\n",
			"VariableInfo": "",
			"Cadence": ""
		},
		{
			"Name": "lon",
			"ShortDescription": "",
			"LongDescription": "Longitude in degree (-180 to 180)",
			"Header": "# ******************************************************* \n#  WARNING: Increase time period selected for listing. \n# ******************************************************* \n# \n#              ************************************\n#              *****    GLOBAL ATTRIBUTES    ******\n#              ************************************\n#\n#     PROJECT                         Alouette>International Satellite for Ionosphere Studies\n#                                     NSSDC>Archived Data\n#     DISCIPLINE                      Space Physics>Ionospheric Science\n#     SOURCE_NAME                     Alouette-2>International Satellite for Ionosphere Studies 2\n#     DATA_TYPE                       NEPROF>Density Profiles\n#     DESCRIPTOR                      TOPS>Topside Sounder\n#     DATA_VERSION                    1\n#     TITLE                           CRC Electron Density Profiles\n#     TEXT                            This data file contains topside electron density profiles as deduced from Alouette                     \n#     TEXT                             2 topside sounder measurements. The data processing was done in the seventies                         \n#     TEXT                             at the Communications Research Center in Ottawa, Canada This data set provides                        \n#     TEXT                             data from 1000km down in steps of irregular step size. The x- and o-traces                            \n#     TEXT                             were manually  scaled from the ionograms and the inversion algorithm of J.                            \n#                                      Jackson was used to compute the density profiles from these traces.                                   \n#     ADID_REF                        NSSD0110\n#     LOGICAL_FILE_ID                 alouette2_neprof_tops_00000000_v01\n#     LOGICAL_SOURCE                  alouette2_neprof_tops\n#     LOGICAL_SOURCE_DESCRIPTION      Alouette-2 CRC Electron Density Profiles\n#     PI_NAME                         J. E. Jackson\n#     PI_AFFILIATION                  Communication Research Centre (CRC), Ottawa\n#     MISSION_GROUP                   Alouette\n#                                     !___ITM Data including Earth Imaging and Ground-Based\n#     INSTRUMENT_TYPE                 Imaging and Remote Sensing (ITM/Earth)\n#     NSSDC_ID                        SPIO-00183\n#     LINK_TEXT                       Alouette2 full listing\n#     LINK_TITLE                      (shows data availability)\n#                                     http://cdaweb.gsfc.nasa.gov/ISIS_ALOUETTE_DOCS/ALOUETTE2_NEPROF_TOPS_full_listing.txt                  \n#\n#  \n# Key Parameter and Survey data (labels K0,K1,K2) are preliminary browse data.\n# Generated by CDAWeb on: Thu Jan 15 18:02:04 2015\n",
			"VariableInfo": "",
			"Cadence": ""
		},
		{
			"Name": "lat",
			"ShortDescription": "",
			"LongDescription": "Latitude in degree",
			"Header": "# ******************************************************* \n#  WARNING: Increase time period selected for listing. \n# ******************************************************* \n# \n#              ************************************\n#              *****    GLOBAL ATTRIBUTES    ******\n#              ************************************\n#\n#     PROJECT                         Alouette>International Satellite for Ionosphere Studies\n#                                     NSSDC>Archived Data\n#     DISCIPLINE                      Space Physics>Ionospheric Science\n#     SOURCE_NAME                     Alouette-2>International Satellite for Ionosphere Studies 2\n#     DATA_TYPE                       NEPROF>Density Profiles\n#     DESCRIPTOR                      TOPS>Topside Sounder\n#     DATA_VERSION                    1\n#     TITLE                           CRC Electron Density Profiles\n#     TEXT                            This data file contains topside electron density profiles as deduced from Alouette                     \n#     TEXT                             2 topside sounder measurements. The data processing was done in the seventies                         \n#     TEXT                             at the Communications Research Center in Ottawa, Canada This data set provides                        \n#     TEXT                             data from 1000km down in steps of irregular step size. The x- and o-traces                            \n#     TEXT                             were manually  scaled from the ionograms and the inversion algorithm of J.                            \n#                                      Jackson was used to compute the density profiles from these traces.                                   \n#     ADID_REF                        NSSD0110\n#     LOGICAL_FILE_ID                 alouette2_neprof_tops_00000000_v01\n#     LOGICAL_SOURCE                  alouette2_neprof_tops\n#     LOGICAL_SOURCE_DESCRIPTION      Alouette-2 CRC Electron Density Profiles\n#     PI_NAME                         J. E. Jackson\n#     PI_AFFILIATION                  Communication Research Centre (CRC), Ottawa\n#     MISSION_GROUP                   Alouette\n#                                     !___ITM Data including Earth Imaging and Ground-Based\n#     INSTRUMENT_TYPE                 Imaging and Remote Sensing (ITM/Earth)\n#     NSSDC_ID                        SPIO-00183\n#     LINK_TEXT                       Alouette2 full listing\n#     LINK_TITLE                      (shows data availability)\n#                                     http://cdaweb.gsfc.nasa.gov/ISIS_ALOUETTE_DOCS/ALOUETTE2_NEPROF_TOPS_full_listing.txt                  \n#\n#  \n# Key Parameter and Survey data (labels K0,K1,K2) are preliminary browse data.\n# Generated by CDAWeb on: Thu Jan 15 18:02:04 2015\n",
			"VariableInfo": "",
			"Cadence": ""
		},
		{
			"Name": "dip",
			"ShortDescription": "",
			"LongDescription": "Magnetic Inclination in degree",
			"Header": "# ******************************************************* \n#  WARNING: Increase time period selected for listing. \n# ******************************************************* \n# \n#              ************************************\n#              *****    GLOBAL ATTRIBUTES    ******\n#              ************************************\n#\n#     PROJECT                         Alouette>International Satellite for Ionosphere Studies\n#                                     NSSDC>Archived Data\n#     DISCIPLINE                      Space Physics>Ionospheric Science\n#     SOURCE_NAME                     Alouette-2>International Satellite for Ionosphere Studies 2\n#     DATA_TYPE                       NEPROF>Density Profiles\n#     DESCRIPTOR                      TOPS>Topside Sounder\n#     DATA_VERSION                    1\n#     TITLE                           CRC Electron Density Profiles\n#     TEXT                            This data file contains topside electron density profiles as deduced from Alouette                     \n#     TEXT                             2 topside sounder measurements. The data processing was done in the seventies                         \n#     TEXT                             at the Communications Research Center in Ottawa, Canada This data set provides                        \n#     TEXT                             data from 1000km down in steps of irregular step size. The x- and o-traces                            \n#     TEXT                             were manually  scaled from the ionograms and the inversion algorithm of J.                            \n#                                      Jackson was used to compute the density profiles from these traces.                                   \n#     ADID_REF                        NSSD0110\n#     LOGICAL_FILE_ID                 alouette2_neprof_tops_00000000_v01\n#     LOGICAL_SOURCE                  alouette2_neprof_tops\n#     LOGICAL_SOURCE_DESCRIPTION      Alouette-2 CRC Electron Density Profiles\n#     PI_NAME                         J. E. Jackson\n#     PI_AFFILIATION                  Communication Research Centre (CRC), Ottawa\n#     MISSION_GROUP                   Alouette\n#                                     !___ITM Data including Earth Imaging and Ground-Based\n#     INSTRUMENT_TYPE                 Imaging and Remote Sensing (ITM/Earth)\n#     NSSDC_ID                        SPIO-00183\n#     LINK_TEXT                       Alouette2 full listing\n#     LINK_TITLE                      (shows data availability)\n#                                     http://cdaweb.gsfc.nasa.gov/ISIS_ALOUETTE_DOCS/ALOUETTE2_NEPROF_TOPS_full_listing.txt                  \n#\n#  \n# Key Parameter and Survey data (labels K0,K1,K2) are preliminary browse data.\n# Generated by CDAWeb on: Thu Jan 15 18:02:04 2015\n",
			"VariableInfo": "",
			"Cadence": ""
		},
		{
			"Name": "L",
			"ShortDescription": "",
			"LongDescription": "L value",
			"Header": "# ******************************************************* \n#  WARNING: Increase time period selected for listing. \n# ******************************************************* \n# \n#              ************************************\n#              *****    GLOBAL ATTRIBUTES    ******\n#              ************************************\n#\n#     PROJECT                         Alouette>International Satellite for Ionosphere Studies\n#                                     NSSDC>Archived Data\n#     DISCIPLINE                      Space Physics>Ionospheric Science\n#     SOURCE_NAME                     Alouette-2>International Satellite for Ionosphere Studies 2\n#     DATA_TYPE                       NEPROF>Density Profiles\n#     DESCRIPTOR                      TOPS>Topside Sounder\n#     DATA_VERSION                    1\n#     TITLE                           CRC Electron Density Profiles\n#     TEXT                            This data file contains topside electron density profiles as deduced from Alouette                     \n#     TEXT                             2 topside sounder measurements. The data processing was done in the seventies                         \n#     TEXT                             at the Communications Research Center in Ottawa, Canada This data set provides                        \n#     TEXT                             data from 1000km down in steps of irregular step size. The x- and o-traces                            \n#     TEXT                             were manually  scaled from the ionograms and the inversion algorithm of J.                            \n#                                      Jackson was used to compute the density profiles from these traces.                                   \n#     ADID_REF                        NSSD0110\n#     LOGICAL_FILE_ID                 alouette2_neprof_tops_00000000_v01\n#     LOGICAL_SOURCE                  alouette2_neprof_tops\n#     LOGICAL_SOURCE_DESCRIPTION      Alouette-2 CRC Electron Density Profiles\n#     PI_NAME                         J. E. Jackson\n#     PI_AFFILIATION                  Communication Research Centre (CRC), Ottawa\n#     MISSION_GROUP                   Alouette\n#                                     !___ITM Data including Earth Imaging and Ground-Based\n#     INSTRUMENT_TYPE                 Imaging and Remote Sensing (ITM/Earth)\n#     NSSDC_ID                        SPIO-00183\n#     LINK_TEXT                       Alouette2 full listing\n#     LINK_TITLE                      (shows data availability)\n#                                     http://cdaweb.gsfc.nasa.gov/ISIS_ALOUETTE_DOCS/ALOUETTE2_NEPROF_TOPS_full_listing.txt                  \n#\n#  \n# Key Parameter and Survey data (labels K0,K1,K2) are preliminary browse data.\n# Generated by CDAWeb on: Thu Jan 15 18:02:05 2015\n",
			"VariableInfo": "",
			"Cadence": ""
		},
		{
			"Name": "sza",
			"ShortDescription": "",
			"LongDescription": "solar zenith angle at 100 km",
			"Header": "# ******************************************************* \n#  WARNING: Increase time period selected for listing. \n# ******************************************************* \n# \n#              ************************************\n#              *****    GLOBAL ATTRIBUTES    ******\n#              ************************************\n#\n#     PROJECT                         Alouette>International Satellite for Ionosphere Studies\n#                                     NSSDC>Archived Data\n#     DISCIPLINE                      Space Physics>Ionospheric Science\n#     SOURCE_NAME                     Alouette-2>International Satellite for Ionosphere Studies 2\n#     DATA_TYPE                       NEPROF>Density Profiles\n#     DESCRIPTOR                      TOPS>Topside Sounder\n#     DATA_VERSION                    1\n#     TITLE                           CRC Electron Density Profiles\n#     TEXT                            This data file contains topside electron density profiles as deduced from Alouette                     \n#     TEXT                             2 topside sounder measurements. The data processing was done in the seventies                         \n#     TEXT                             at the Communications Research Center in Ottawa, Canada This data set provides                        \n#     TEXT                             data from 1000km down in steps of irregular step size. The x- and o-traces                            \n#     TEXT                             were manually  scaled from the ionograms and the inversion algorithm of J.                            \n#                                      Jackson was used to compute the density profiles from these traces.                                   \n#     ADID_REF                        NSSD0110\n#     LOGICAL_FILE_ID                 alouette2_neprof_tops_00000000_v01\n#     LOGICAL_SOURCE                  alouette2_neprof_tops\n#     LOGICAL_SOURCE_DESCRIPTION      Alouette-2 CRC Electron Density Profiles\n#     PI_NAME                         J. E. Jackson\n#     PI_AFFILIATION                  Communication Research Centre (CRC), Ottawa\n#     MISSION_GROUP                   Alouette\n#                                     !___ITM Data including Earth Imaging and Ground-Based\n#     INSTRUMENT_TYPE                 Imaging and Remote Sensing (ITM/Earth)\n#     NSSDC_ID                        SPIO-00183\n#     LINK_TEXT                       Alouette2 full listing\n#     LINK_TITLE                      (shows data availability)\n#                                     http://cdaweb.gsfc.nasa.gov/ISIS_ALOUETTE_DOCS/ALOUETTE2_NEPROF_TOPS_full_listing.txt                  \n#\n#  \n# Key Parameter and Survey data (labels K0,K1,K2) are preliminary browse data.\n# Generated by CDAWeb on: Thu Jan 15 18:02:05 2015\n",
			"VariableInfo": "",
			"Cadence": ""
		},
		{
			"Name": "sunspotNumber",
			"ShortDescription": "label",
			"LongDescription": "12-month-running mean of sunspot number",
			"Header": "# ******************************************************* \n#  WARNING: Increase time period selected for listing. \n# ******************************************************* \n# \n#              ************************************\n#              *****    GLOBAL ATTRIBUTES    ******\n#              ************************************\n#\n#     PROJECT                         Alouette>International Satellite for Ionosphere Studies\n#                                     NSSDC>Archived Data\n#     DISCIPLINE                      Space Physics>Ionospheric Science\n#     SOURCE_NAME                     Alouette-2>International Satellite for Ionosphere Studies 2\n#     DATA_TYPE                       NEPROF>Density Profiles\n#     DESCRIPTOR                      TOPS>Topside Sounder\n#     DATA_VERSION                    1\n#     TITLE                           CRC Electron Density Profiles\n#     TEXT                            This data file contains topside electron density profiles as deduced from Alouette                     \n#     TEXT                             2 topside sounder measurements. The data processing was done in the seventies                         \n#     TEXT                             at the Communications Research Center in Ottawa, Canada This data set provides                        \n#     TEXT                             data from 1000km down in steps of irregular step size. The x- and o-traces                            \n#     TEXT                             were manually  scaled from the ionograms and the inversion algorithm of J.                            \n#                                      Jackson was used to compute the density profiles from these traces.                                   \n#     ADID_REF                        NSSD0110\n#     LOGICAL_FILE_ID                 alouette2_neprof_tops_00000000_v01\n#     LOGICAL_SOURCE                  alouette2_neprof_tops\n#     LOGICAL_SOURCE_DESCRIPTION      Alouette-2 CRC Electron Density Profiles\n#     PI_NAME                         J. E. Jackson\n#     PI_AFFILIATION                  Communication Research Centre (CRC), Ottawa\n#     MISSION_GROUP                   Alouette\n#                                     !___ITM Data including Earth Imaging and Ground-Based\n#     INSTRUMENT_TYPE                 Imaging and Remote Sensing (ITM/Earth)\n#     NSSDC_ID                        SPIO-00183\n#     LINK_TEXT                       Alouette2 full listing\n#     LINK_TITLE                      (shows data availability)\n#                                     http://cdaweb.gsfc.nasa.gov/ISIS_ALOUETTE_DOCS/ALOUETTE2_NEPROF_TOPS_full_listing.txt                  \n#\n#  \n# Key Parameter and Survey data (labels K0,K1,K2) are preliminary browse data.\n# Generated by CDAWeb on: Thu Jan 15 18:02:06 2015\n",
			"VariableInfo": "",
			"Cadence": ""
		},
		{
			"Name": "IGindex",
			"ShortDescription": "label",
			"LongDescription": "12-month-running mean of IG ionosonde index",
			"Header": "# ******************************************************* \n#  WARNING: Increase time period selected for listing. \n# ******************************************************* \n# \n#              ************************************\n#              *****    GLOBAL ATTRIBUTES    ******\n#              ************************************\n#\n#     PROJECT                         Alouette>International Satellite for Ionosphere Studies\n#                                     NSSDC>Archived Data\n#     DISCIPLINE                      Space Physics>Ionospheric Science\n#     SOURCE_NAME                     Alouette-2>International Satellite for Ionosphere Studies 2\n#     DATA_TYPE                       NEPROF>Density Profiles\n#     DESCRIPTOR                      TOPS>Topside Sounder\n#     DATA_VERSION                    1\n#     TITLE                           CRC Electron Density Profiles\n#     TEXT                            This data file contains topside electron density profiles as deduced from Alouette                     \n#     TEXT                             2 topside sounder measurements. The data processing was done in the seventies                         \n#     TEXT                             at the Communications Research Center in Ottawa, Canada This data set provides                        \n#     TEXT                             data from 1000km down in steps of irregular step size. The x- and o-traces                            \n#     TEXT                             were manually  scaled from the ionograms and the inversion algorithm of J.                            \n#                                      Jackson was used to compute the density profiles from these traces.                                   \n#     ADID_REF                        NSSD0110\n#     LOGICAL_FILE_ID                 alouette2_neprof_tops_00000000_v01\n#     LOGICAL_SOURCE                  alouette2_neprof_tops\n#     LOGICAL_SOURCE_DESCRIPTION      Alouette-2 CRC Electron Density Profiles\n#     PI_NAME                         J. E. Jackson\n#     PI_AFFILIATION                  Communication Research Centre (CRC), Ottawa\n#     MISSION_GROUP                   Alouette\n#                                     !___ITM Data including Earth Imaging and Ground-Based\n#     INSTRUMENT_TYPE                 Imaging and Remote Sensing (ITM/Earth)\n#     NSSDC_ID                        SPIO-00183\n#     LINK_TEXT                       Alouette2 full listing\n#     LINK_TITLE                      (shows data availability)\n#                                     http://cdaweb.gsfc.nasa.gov/ISIS_ALOUETTE_DOCS/ALOUETTE2_NEPROF_TOPS_full_listing.txt                  \n#\n#  \n# Key Parameter and Survey data (labels K0,K1,K2) are preliminary browse data.\n# Generated by CDAWeb on: Thu Jan 15 18:02:06 2015\n",
			"VariableInfo": "",
			"Cadence": ""
		}
	]
}