{
	"Id": "C2_CP_FGM_SPIN",
	"Observatory": [
		"C2"
	],
	"Instrument": [
		"FGM"
	],
	"ObservatoryGroup": [
		"Cluster"
	],
	"InstrumentType": [
		"Magnetic Fields (space)"
	],
	"Label": "Cluster Spacecraft 2 FluxGate Magnetometer (FGM) Spin-Resolution Parameters - Andre Balogh>a.balogh@imperial.ac.uk & Elizabeth Lucek>e.lucek@imperial.ac.uk & ESA CAA (Imperial College)",
	"TimeInterval": {
		"Start": "2001-01-30T22:56:54.000Z",
		"End": "2014-05-01T06:05:44.000Z"
	},
	"PiName": "Andre Balogh>a.balogh@imperial.ac.uk & Elizabeth Lucek>e.lucek@imperial.ac.uk & ESA CAA",
	"PiAffiliation": "Imperial College",
	"Notes": "http://cdaweb.gsfc.nasa.gov/misc/NotesC.html#C2_CP_FGM_SPIN",
	"DatasetLink": [
		{
			"Title": "Cluster Science Archive",
			"Text": "Higher-Resolution FGM and other instrument parameters from the",
			"Url": "http://www.cosmos.esa.int/web/csa"
		},
		{
			"Title": "Instrument Home Page",
			"Text": "Cluster Magnetometer",
			"Url": "http://www3.imperial.ac.uk/spat/research/missions/space_missions/clusterhomepage/clustermagnetometerinstrument/"
		}
	],
	"VariableDescription": [
		{
			"Name": "B_vec_xyz_gse__C2_CP_FGM_SPIN",
			"ShortDescription": "",
			"LongDescription": "Cluster C2, Magnetic Field Vector, spin resolution in GSE",
			"Header": "#              ************************************\n#              *****    GLOBAL ATTRIBUTES    ******\n#              ************************************\n#\n#     PROJECT                         Cluster\n#     MISSION_GROUP                   Cluster\n#     SOURCE_NAME                     C2>Cluster spacecraft 2\n#     DESCRIPTOR                      FGM>FluxGate Magnetometer Spin Resolution\n#     INSTRUMENT_TYPE                 Magnetic Fields (space)\n#     LOGICAL_SOURCE                  C2_CP_FGM_SPIN\n#     LOGICAL_SOURCE_DESCRIPTION      Cluster Spacecraft 2 FluxGate Magnetometer (FGM) Spin-Resolution Parameters\n#     LOGICAL_FILE_ID                 C2_CP_FGM_SPIN_00000000_v01\n#     MISSION                         Cluster\n#     PI_NAME                         Andre Balogh>a.balogh@imperial.ac.uk & Elizabeth Lucek>e.lucek@imperial.ac.uk                          \n#                                      & ESA CAA                                                                                             \n#     PI_AFFILIATION                  Imperial College\n#     MISSION_TIME_SPAN               6.3133649e+13\n#     MISSION_AGENCY                  ESA\n#                                     The aim of the Cluster mission is to study small-scale structures of the magnetosphere                 \n#                                     and its environment in three dimensions. To achieve this, Cluster is constituted                       \n#                                      of four                                                                                               \n#                                     identical spacecraft that will flight in a tetrahedral configuration. The separation                   \n#                                      distances                                                                                             \n#                                     between the spacecraft will be varied between 600 km and 20 000 km, according                          \n#                                      to the                                                                                                \n#                                     key scientific regions.\n#     MISSION_KEY_PERSONNEL           Philippe Escoubet>Philippe.Escoubet@esa.int >Cluster Project Scientist\n#     MISSION_REFERENCES              The Cluster and Phoenix Missions>Cluster project and instrument teams>Space                            \n#                                      Sci. Rev. 79, Nos. 1-2, 1997                                                                          \n#     MISSION_REGION                  Solar_Wind\n#                                     Bow_Shock\n#                                     Magnetosheath\n#                                     Magnetopause\n#                                     Magnetosphere\n#                                     Magnetotail\n#                                     Polar_Cap\n#                                     Auroral_Region\n#                                     Cusp\n#                                     Radiation_Belt\n#                                     Plasmasphere\n#     MISSION_CAVEATS                 *CL\n#     OBSERVATORY                     Cluster-1\n#     OBSERVATORY_CAVEATS             *C2_CQ\n#     OBSERVATORY_DESCRIPTION         Cluster-1 (Rumba)\n#                                     Launched: 09 Aug 2000\n#                                     ESA Number: 1\n#                                     COSPAR ID: 2000-045A\n#                                     USSPACECOM catalogue number 26463\n#                                     CSDS Code: C2\n#                                     ESOC FD code: S1\n#                                     ESA Flight Model Number: FM5\n#     OBSERVATORY_TIME_SPAN           6.3130970e+13\n#     OBSERVATORY_REGION              Solar_Wind\n#                                     Bow_Shock\n#                                     Magnetosheath\n#                                     Magnetopause\n#                                     Magnetosphere\n#                                     Magnetotail\n#                                     Polar_Cap\n#                                     Auroral_Region\n#                                     Cusp\n#                                     Radiation_Belt\n#                                     Plasmasphere\n#     EXPERIMENT                      FGM\n#     EXPERIMENT_DESCRIPTION          Fluxgate Magnetometer\n#     INVESTIGATOR_COORDINATES        Andre Balogh>PI>a.balogh@imperial.ac.uk\n#                                     Elizabeth Lucek>PI>e.lucek@imperial.ac.uk\n#     EXPERIMENT_REFERENCES           *CL_CD_CAA_FGM_ICD_0001_V0_1.pdf\n#                                     *CL_CD_FGM_USERMAN.pdf\n#                                     http://www.sp.ph.ic.ac.uk/Cluster/\n#     EXPERIMENT_KEY_PERSONNEL        Andre Balogh>PI>a.balogh@imperial.ac.uk\n#                                     Elizabeth Lucek>PI>e.lucek@imperial.ac.uk\n#     EXPERIMENT_CAVEATS              *CL_CQ_FGM_CAVF.txt\n#     MEASUREMENT_TYPE                Magnetic_Field\n#     ACKNOWLEDGEMENT                 Please acknowledge the FGM team and ESA Cluster Active\n#                                     Archive in any publication based upon use of this data.\n#     INSTRUMENT_NAME                 FGM1\n#     INSTRUMENT_DESCRIPTION          FGM Experiment on Cluster C2\n#     INSTRUMENT_CAVEATS              *C2_CQ_FGM_CAVF\n#     DATASET_ID                      C2_CP_FGM_SPIN\n#     DATA_TYPE                       CP>CAA Parameter\n#     DATASET_TITLE                   Magnetic field, spin resolution\n#     DATASET_DESCRIPTION             This dataset contains spin resolution measurements of the magnetic field vector                        \n#                                      from the FGM                                                                                          \n#                                     experiment on the Cluster C2 spacecraft\n#     CONTACT_COORDINATES             Elizabeth Lucek>PI>e.lucek@imperial.ac.uk\n#     TIME_RESOLUTION                 4\n#     MIN_TIME_RESOLUTION             4.412\n#     MAX_TIME_RESOLUTION             3.636\n#     PROCESSING_LEVEL                Calibrated\n#     DATASET_CAVEATS                 *C2_CQ_FGM_CAVF\n#     VERSION_NUMBER                  050922\n#     DATASET_VERSION                 Merged file, the dataset version for each segment follows:-\n#                                     2001-02-01T00:00:00Z/2001-02-02T00:00:00Z , C2_CP_FGM_SPIN__20010130_191835_20010202_042434_V01        \n#                                     01\n#     FILE_CAVEATS                    CAA Merged File - $Id: cefmerge.c,v 1.13 2007/02/23 14:03:48 cperry Exp cperry $\n#                                     The file caveats for each segment follows:-\n#                                     2001-02-01T00:00:00Z/2001-02-02T00:00:00Z , C2_CP_FGM_SPIN__20010130_191835_20010202_042434_V01        \n#                                     Calibration parameters have been estimated using the Fourier analysis method                           \n#                                      and solar wind analysis                                                                               \n#     FILE_TYPE                       cef\n#     METADATA_TYPE                   CAA\n#     METADATA_VERSION                2.0\n#     FILE_TIME_SPAN                  6.3148205e+13\n#     GENERATION_DATE                 6.3348440e+13\n#     SOFTWARE_VERSION                QIE V_3.4.8 [Feb 2007]\n#     LINK_TEXT                       Higher-Resolution FGM and other instrument parameters from the\n#                                     Cluster Magnetometer\n#     LINK_TITLE                      Cluster Science Archive\n#                                     Instrument Home Page\n#     HTTP_LINK                       http://www.cosmos.esa.int/web/csa\n#                                     http://www3.imperial.ac.uk/spat/research/missions/space_missions/clusterhomepage/clustermagnetometerins\n#     SPASE_DATASETRESOURCEID         spase://VMO/NumericalData/Cluster-Salsa/FGM/SpinResolution/4S\n#\n#              ************************************\n#              ****  RECORD VARYING VARIABLES  ****\n#              ************************************\n#\n#  1. Interval centred time tag\n#  2. Cluster C2, Magnetic Field Vector, spin resolution in GSE\n#\n#  \n# Key Parameter and Survey data (labels K0,K1,K2) are preliminary browse data.\n# Generated by CDAWeb on: Thu Jan 15 19:12:24 2015\n",
			"VariableInfo": "#\nUT                                      BX_GSE                 BY_GSE                 BZ_GSE\n                                   (@_Bx GSE_)            (@_By GSE_)            (@_Bz GSE_)\ndd-mm-yyyy hh:mm:ss.ms                      nT                     nT                     nT\n30-01-2001 22:56:54.632                39.1720               -50.3330               -162.177",
			"Cadence": "4017,4018"
		},
		{
			"Name": "B_mag__C2_CP_FGM_SPIN",
			"ShortDescription": "",
			"LongDescription": "Cluster C2, Magnetic Field Magnitude, spin resolution",
			"Header": "#              ************************************\n#              *****    GLOBAL ATTRIBUTES    ******\n#              ************************************\n#\n#     PROJECT                         Cluster\n#     MISSION_GROUP                   Cluster\n#     SOURCE_NAME                     C2>Cluster spacecraft 2\n#     DESCRIPTOR                      FGM>FluxGate Magnetometer Spin Resolution\n#     INSTRUMENT_TYPE                 Magnetic Fields (space)\n#     LOGICAL_SOURCE                  C2_CP_FGM_SPIN\n#     LOGICAL_SOURCE_DESCRIPTION      Cluster Spacecraft 2 FluxGate Magnetometer (FGM) Spin-Resolution Parameters\n#     LOGICAL_FILE_ID                 C2_CP_FGM_SPIN_00000000_v01\n#     MISSION                         Cluster\n#     PI_NAME                         Andre Balogh>a.balogh@imperial.ac.uk & Elizabeth Lucek>e.lucek@imperial.ac.uk                          \n#                                      & ESA CAA                                                                                             \n#     PI_AFFILIATION                  Imperial College\n#     MISSION_TIME_SPAN               6.3133649e+13\n#     MISSION_AGENCY                  ESA\n#                                     The aim of the Cluster mission is to study small-scale structures of the magnetosphere                 \n#                                     and its environment in three dimensions. To achieve this, Cluster is constituted                       \n#                                      of four                                                                                               \n#                                     identical spacecraft that will flight in a tetrahedral configuration. The separation                   \n#                                      distances                                                                                             \n#                                     between the spacecraft will be varied between 600 km and 20 000 km, according                          \n#                                      to the                                                                                                \n#                                     key scientific regions.\n#     MISSION_KEY_PERSONNEL           Philippe Escoubet>Philippe.Escoubet@esa.int >Cluster Project Scientist\n#     MISSION_REFERENCES              The Cluster and Phoenix Missions>Cluster project and instrument teams>Space                            \n#                                      Sci. Rev. 79, Nos. 1-2, 1997                                                                          \n#     MISSION_REGION                  Solar_Wind\n#                                     Bow_Shock\n#                                     Magnetosheath\n#                                     Magnetopause\n#                                     Magnetosphere\n#                                     Magnetotail\n#                                     Polar_Cap\n#                                     Auroral_Region\n#                                     Cusp\n#                                     Radiation_Belt\n#                                     Plasmasphere\n#     MISSION_CAVEATS                 *CL\n#     OBSERVATORY                     Cluster-1\n#     OBSERVATORY_CAVEATS             *C2_CQ\n#     OBSERVATORY_DESCRIPTION         Cluster-1 (Rumba)\n#                                     Launched: 09 Aug 2000\n#                                     ESA Number: 1\n#                                     COSPAR ID: 2000-045A\n#                                     USSPACECOM catalogue number 26463\n#                                     CSDS Code: C2\n#                                     ESOC FD code: S1\n#                                     ESA Flight Model Number: FM5\n#     OBSERVATORY_TIME_SPAN           6.3130970e+13\n#     OBSERVATORY_REGION              Solar_Wind\n#                                     Bow_Shock\n#                                     Magnetosheath\n#                                     Magnetopause\n#                                     Magnetosphere\n#                                     Magnetotail\n#                                     Polar_Cap\n#                                     Auroral_Region\n#                                     Cusp\n#                                     Radiation_Belt\n#                                     Plasmasphere\n#     EXPERIMENT                      FGM\n#     EXPERIMENT_DESCRIPTION          Fluxgate Magnetometer\n#     INVESTIGATOR_COORDINATES        Andre Balogh>PI>a.balogh@imperial.ac.uk\n#                                     Elizabeth Lucek>PI>e.lucek@imperial.ac.uk\n#     EXPERIMENT_REFERENCES           *CL_CD_CAA_FGM_ICD_0001_V0_1.pdf\n#                                     *CL_CD_FGM_USERMAN.pdf\n#                                     http://www.sp.ph.ic.ac.uk/Cluster/\n#     EXPERIMENT_KEY_PERSONNEL        Andre Balogh>PI>a.balogh@imperial.ac.uk\n#                                     Elizabeth Lucek>PI>e.lucek@imperial.ac.uk\n#     EXPERIMENT_CAVEATS              *CL_CQ_FGM_CAVF.txt\n#     MEASUREMENT_TYPE                Magnetic_Field\n#     ACKNOWLEDGEMENT                 Please acknowledge the FGM team and ESA Cluster Active\n#                                     Archive in any publication based upon use of this data.\n#     INSTRUMENT_NAME                 FGM1\n#     INSTRUMENT_DESCRIPTION          FGM Experiment on Cluster C2\n#     INSTRUMENT_CAVEATS              *C2_CQ_FGM_CAVF\n#     DATASET_ID                      C2_CP_FGM_SPIN\n#     DATA_TYPE                       CP>CAA Parameter\n#     DATASET_TITLE                   Magnetic field, spin resolution\n#     DATASET_DESCRIPTION             This dataset contains spin resolution measurements of the magnetic field vector                        \n#                                      from the FGM                                                                                          \n#                                     experiment on the Cluster C2 spacecraft\n#     CONTACT_COORDINATES             Elizabeth Lucek>PI>e.lucek@imperial.ac.uk\n#     TIME_RESOLUTION                 4\n#     MIN_TIME_RESOLUTION             4.412\n#     MAX_TIME_RESOLUTION             3.636\n#     PROCESSING_LEVEL                Calibrated\n#     DATASET_CAVEATS                 *C2_CQ_FGM_CAVF\n#     VERSION_NUMBER                  050922\n#     DATASET_VERSION                 Merged file, the dataset version for each segment follows:-\n#                                     2001-02-01T00:00:00Z/2001-02-02T00:00:00Z , C2_CP_FGM_SPIN__20010130_191835_20010202_042434_V01        \n#                                     01\n#     FILE_CAVEATS                    CAA Merged File - $Id: cefmerge.c,v 1.13 2007/02/23 14:03:48 cperry Exp cperry $\n#                                     The file caveats for each segment follows:-\n#                                     2001-02-01T00:00:00Z/2001-02-02T00:00:00Z , C2_CP_FGM_SPIN__20010130_191835_20010202_042434_V01        \n#                                     Calibration parameters have been estimated using the Fourier analysis method                           \n#                                      and solar wind analysis                                                                               \n#     FILE_TYPE                       cef\n#     METADATA_TYPE                   CAA\n#     METADATA_VERSION                2.0\n#     FILE_TIME_SPAN                  6.3148205e+13\n#     GENERATION_DATE                 6.3348440e+13\n#     SOFTWARE_VERSION                QIE V_3.4.8 [Feb 2007]\n#     LINK_TEXT                       Higher-Resolution FGM and other instrument parameters from the\n#                                     Cluster Magnetometer\n#     LINK_TITLE                      Cluster Science Archive\n#                                     Instrument Home Page\n#     HTTP_LINK                       http://www.cosmos.esa.int/web/csa\n#                                     http://www3.imperial.ac.uk/spat/research/missions/space_missions/clusterhomepage/clustermagnetometerins\n#     SPASE_DATASETRESOURCEID         spase://VMO/NumericalData/Cluster-Salsa/FGM/SpinResolution/4S\n#\n#              ************************************\n#              ****  RECORD VARYING VARIABLES  ****\n#              ************************************\n#\n#  1. Interval centred time tag\n#  2. Cluster C2, Magnetic Field Magnitude, spin resolution\n#\n#  \n# Key Parameter and Survey data (labels K0,K1,K2) are preliminary browse data.\n# Generated by CDAWeb on: Thu Jan 15 19:12:25 2015\n",
			"VariableInfo": "#  2. Cluster C2, Magnetic Field Magnitude, spin resolution\n#\nUT                                  B\ndd-mm-yyyy hh:mm:ss.ms             nT\n30-01-2001 22:56:54.632       174.268",
			"Cadence": "4017,4018"
		},
		{
			"Name": "sc_pos_xyz_gse__C2_CP_FGM_SPIN",
			"ShortDescription": "",
			"LongDescription": "Position of Cluster C2 in GSE",
			"Header": "#              ************************************\n#              *****    GLOBAL ATTRIBUTES    ******\n#              ************************************\n#\n#     PROJECT                         Cluster\n#     MISSION_GROUP                   Cluster\n#     SOURCE_NAME                     C2>Cluster spacecraft 2\n#     DESCRIPTOR                      FGM>FluxGate Magnetometer Spin Resolution\n#     INSTRUMENT_TYPE                 Magnetic Fields (space)\n#     LOGICAL_SOURCE                  C2_CP_FGM_SPIN\n#     LOGICAL_SOURCE_DESCRIPTION      Cluster Spacecraft 2 FluxGate Magnetometer (FGM) Spin-Resolution Parameters\n#     LOGICAL_FILE_ID                 C2_CP_FGM_SPIN_00000000_v01\n#     MISSION                         Cluster\n#     PI_NAME                         Andre Balogh>a.balogh@imperial.ac.uk & Elizabeth Lucek>e.lucek@imperial.ac.uk                          \n#                                      & ESA CAA                                                                                             \n#     PI_AFFILIATION                  Imperial College\n#     MISSION_TIME_SPAN               6.3133649e+13\n#     MISSION_AGENCY                  ESA\n#                                     The aim of the Cluster mission is to study small-scale structures of the magnetosphere                 \n#                                     and its environment in three dimensions. To achieve this, Cluster is constituted                       \n#                                      of four                                                                                               \n#                                     identical spacecraft that will flight in a tetrahedral configuration. The separation                   \n#                                      distances                                                                                             \n#                                     between the spacecraft will be varied between 600 km and 20 000 km, according                          \n#                                      to the                                                                                                \n#                                     key scientific regions.\n#     MISSION_KEY_PERSONNEL           Philippe Escoubet>Philippe.Escoubet@esa.int >Cluster Project Scientist\n#     MISSION_REFERENCES              The Cluster and Phoenix Missions>Cluster project and instrument teams>Space                            \n#                                      Sci. Rev. 79, Nos. 1-2, 1997                                                                          \n#     MISSION_REGION                  Solar_Wind\n#                                     Bow_Shock\n#                                     Magnetosheath\n#                                     Magnetopause\n#                                     Magnetosphere\n#                                     Magnetotail\n#                                     Polar_Cap\n#                                     Auroral_Region\n#                                     Cusp\n#                                     Radiation_Belt\n#                                     Plasmasphere\n#     MISSION_CAVEATS                 *CL\n#     OBSERVATORY                     Cluster-1\n#     OBSERVATORY_CAVEATS             *C2_CQ\n#     OBSERVATORY_DESCRIPTION         Cluster-1 (Rumba)\n#                                     Launched: 09 Aug 2000\n#                                     ESA Number: 1\n#                                     COSPAR ID: 2000-045A\n#                                     USSPACECOM catalogue number 26463\n#                                     CSDS Code: C2\n#                                     ESOC FD code: S1\n#                                     ESA Flight Model Number: FM5\n#     OBSERVATORY_TIME_SPAN           6.3130970e+13\n#     OBSERVATORY_REGION              Solar_Wind\n#                                     Bow_Shock\n#                                     Magnetosheath\n#                                     Magnetopause\n#                                     Magnetosphere\n#                                     Magnetotail\n#                                     Polar_Cap\n#                                     Auroral_Region\n#                                     Cusp\n#                                     Radiation_Belt\n#                                     Plasmasphere\n#     EXPERIMENT                      FGM\n#     EXPERIMENT_DESCRIPTION          Fluxgate Magnetometer\n#     INVESTIGATOR_COORDINATES        Andre Balogh>PI>a.balogh@imperial.ac.uk\n#                                     Elizabeth Lucek>PI>e.lucek@imperial.ac.uk\n#     EXPERIMENT_REFERENCES           *CL_CD_CAA_FGM_ICD_0001_V0_1.pdf\n#                                     *CL_CD_FGM_USERMAN.pdf\n#                                     http://www.sp.ph.ic.ac.uk/Cluster/\n#     EXPERIMENT_KEY_PERSONNEL        Andre Balogh>PI>a.balogh@imperial.ac.uk\n#                                     Elizabeth Lucek>PI>e.lucek@imperial.ac.uk\n#     EXPERIMENT_CAVEATS              *CL_CQ_FGM_CAVF.txt\n#     MEASUREMENT_TYPE                Magnetic_Field\n#     ACKNOWLEDGEMENT                 Please acknowledge the FGM team and ESA Cluster Active\n#                                     Archive in any publication based upon use of this data.\n#     INSTRUMENT_NAME                 FGM1\n#     INSTRUMENT_DESCRIPTION          FGM Experiment on Cluster C2\n#     INSTRUMENT_CAVEATS              *C2_CQ_FGM_CAVF\n#     DATASET_ID                      C2_CP_FGM_SPIN\n#     DATA_TYPE                       CP>CAA Parameter\n#     DATASET_TITLE                   Magnetic field, spin resolution\n#     DATASET_DESCRIPTION             This dataset contains spin resolution measurements of the magnetic field vector                        \n#                                      from the FGM                                                                                          \n#                                     experiment on the Cluster C2 spacecraft\n#     CONTACT_COORDINATES             Elizabeth Lucek>PI>e.lucek@imperial.ac.uk\n#     TIME_RESOLUTION                 4\n#     MIN_TIME_RESOLUTION             4.412\n#     MAX_TIME_RESOLUTION             3.636\n#     PROCESSING_LEVEL                Calibrated\n#     DATASET_CAVEATS                 *C2_CQ_FGM_CAVF\n#     VERSION_NUMBER                  050922\n#     DATASET_VERSION                 Merged file, the dataset version for each segment follows:-\n#                                     2001-02-01T00:00:00Z/2001-02-02T00:00:00Z , C2_CP_FGM_SPIN__20010130_191835_20010202_042434_V01        \n#                                     01\n#     FILE_CAVEATS                    CAA Merged File - $Id: cefmerge.c,v 1.13 2007/02/23 14:03:48 cperry Exp cperry $\n#                                     The file caveats for each segment follows:-\n#                                     2001-02-01T00:00:00Z/2001-02-02T00:00:00Z , C2_CP_FGM_SPIN__20010130_191835_20010202_042434_V01        \n#                                     Calibration parameters have been estimated using the Fourier analysis method                           \n#                                      and solar wind analysis                                                                               \n#     FILE_TYPE                       cef\n#     METADATA_TYPE                   CAA\n#     METADATA_VERSION                2.0\n#     FILE_TIME_SPAN                  6.3148205e+13\n#     GENERATION_DATE                 6.3348440e+13\n#     SOFTWARE_VERSION                QIE V_3.4.8 [Feb 2007]\n#     LINK_TEXT                       Higher-Resolution FGM and other instrument parameters from the\n#                                     Cluster Magnetometer\n#     LINK_TITLE                      Cluster Science Archive\n#                                     Instrument Home Page\n#     HTTP_LINK                       http://www.cosmos.esa.int/web/csa\n#                                     http://www3.imperial.ac.uk/spat/research/missions/space_missions/clusterhomepage/clustermagnetometerins\n#     SPASE_DATASETRESOURCEID         spase://VMO/NumericalData/Cluster-Salsa/FGM/SpinResolution/4S\n#\n#              ************************************\n#              ****  RECORD VARYING VARIABLES  ****\n#              ************************************\n#\n#  1. Interval centred time tag\n#  2. Position of Cluster C2 in GSE\n#\n#  \n# Key Parameter and Survey data (labels K0,K1,K2) are preliminary browse data.\n# Generated by CDAWeb on: Thu Jan 15 19:12:25 2015\n",
			"VariableInfo": "#\nUT                                    C2_X_GSE               C2_Y_GSE               C2_Z_GSE\n                              (@_C2 x GSE_GSE)       (@_C2 y GSE_GSE)       (@_C2 z GSE_GSE)\ndd-mm-yyyy hh:mm:ss.ms                      km                     km                     km\n30-01-2001 22:56:54.632               -8700.30                14616.3                42100.8",
			"Cadence": "4017,4018"
		}
	]
}