{
	"Id": "WI_K0_WAV",
	"Observatory": [
		"WIND"
	],
	"Instrument": [
		"WAV"
	],
	"ObservatoryGroup": [
		"Wind"
	],
	"InstrumentType": [
		"Radio and Plasma Waves (space)"
	],
	"Label": "Wind Radio/Plasma Wave, (WAVES) Key Parameters - M. L. Kaiser (GSFC)",
	"TimeInterval": {
		"Start": "1994-11-10T00:01:30.000Z",
		"End": "2015-01-13T23:58:30.000Z"
	},
	"PiName": "M. L. Kaiser",
	"PiAffiliation": "GSFC",
	"Notes": "http://cdaweb.gsfc.nasa.gov/misc/NotesW.html#WI_K0_WAV",
	"DatasetLink": [
		{
			"Title": "Home Page (including daily plots, 1-min avg IDL savesets and radio burst lists).",
			"Text": "Wind WAVES ",
			"Url": "http://www-lep.gsfc.nasa.gov/waves/"
		}
	],
	"VariableDescription": [
		{
			"Name": "E_Average",
			"ShortDescription": "electric_field>average_component",
			"LongDescription": "Electric field average intensity in dB above background at 76 log-spaced frequencies (250-9.4e6 Hz).",
			"Header": "# ******************************************************* \n#  WARNING: Increase time period selected for listing. \n# ******************************************************* \n# \n#              ************************************\n#              *****    GLOBAL ATTRIBUTES    ******\n#              ************************************\n#\n#     PROJECT                         ISTP>International Solar-Terrestrial Physics\n#     DISCIPLINE                      SPACE PHYSICS>Interplanetary Studies\n#     SOURCE_NAME                     WIND>WIND Interplanetary Plasma Laboratory\n#     DATA_TYPE                       K0>KEY PARAMETER\n#     DESCRIPTOR                      WAV>Radio/Plasma Wave\n#     DATA_VERSION                    1\n#     TITLE                           WIND WAVES CDF format\n#     TEXT                            SSR WAVES: The Radio and Plasma Wave Investigation on the WIND Spacecraft, Vol                         \n#                                      71, pg 231-263,1995.                                                                                  \n#     MODS                            CODED MAY 1996, C. MEETRE\n#     ADID_REF                        NSSD0139\n#     LOGICAL_FILE_ID                 WI_K0_WAV_19920908_V01\n#     LOGICAL_SOURCE                  WI_K0_WAV\n#     LOGICAL_SOURCE_DESCRIPTION      Wind Radio/Plasma Wave, (WAVES) Key Parameters\n#     PI_NAME                         M. L. Kaiser\n#     PI_AFFILIATION                  GSFC\n#     INSTRUMENT_TYPE                 Radio and Plasma Waves (space)\n#     LINK_TEXT                       Wind WAVES\n#     LINK_TITLE                      Home Page (including daily plots, 1-min avg IDL savesets and radio burst lists).\n#     HTTP_LINK                       http://www-lep.gsfc.nasa.gov/waves/\n#     NSSDC_ID                        sphe-00652\n#     ALT_LOGICAL_SOURCE              Wind_WAVES_Electric-Field-Intensities_Key-Parameters-K0_3min_cdf\n#     MISSION_GROUP                   Wind\n#                                     !___Interplanetary Data near 1 AU\n#\n#  \n# Key Parameter and Survey data (labels K0,K1,K2) are preliminary browse data.\n# Generated by CDAWeb on: Thu Jan 15 22:54:51 2015\n",
			"VariableInfo": "",
			"Cadence": ""
		},
		{
			"Name": "Ne",
			"ShortDescription": "density>electron",
			"LongDescription": "Electron density determined from insitu Fpe 'line'; position recognized by a neural network.",
			"Header": "# ******************************************************* \n#  WARNING: Increase time period selected for listing. \n# ******************************************************* \n# \n#              ************************************\n#              *****    GLOBAL ATTRIBUTES    ******\n#              ************************************\n#\n#     PROJECT                         ISTP>International Solar-Terrestrial Physics\n#     DISCIPLINE                      SPACE PHYSICS>Interplanetary Studies\n#     SOURCE_NAME                     WIND>WIND Interplanetary Plasma Laboratory\n#     DATA_TYPE                       K0>KEY PARAMETER\n#     DESCRIPTOR                      WAV>Radio/Plasma Wave\n#     DATA_VERSION                    1\n#     TITLE                           WIND WAVES CDF format\n#     TEXT                            SSR WAVES: The Radio and Plasma Wave Investigation on the WIND Spacecraft, Vol                         \n#                                      71, pg 231-263,1995.                                                                                  \n#     MODS                            CODED MAY 1996, C. MEETRE\n#     ADID_REF                        NSSD0139\n#     LOGICAL_FILE_ID                 WI_K0_WAV_19920908_V01\n#     LOGICAL_SOURCE                  WI_K0_WAV\n#     LOGICAL_SOURCE_DESCRIPTION      Wind Radio/Plasma Wave, (WAVES) Key Parameters\n#     PI_NAME                         M. L. Kaiser\n#     PI_AFFILIATION                  GSFC\n#     INSTRUMENT_TYPE                 Radio and Plasma Waves (space)\n#     LINK_TEXT                       Wind WAVES\n#     LINK_TITLE                      Home Page (including daily plots, 1-min avg IDL savesets and radio burst lists).\n#     HTTP_LINK                       http://www-lep.gsfc.nasa.gov/waves/\n#     NSSDC_ID                        sphe-00652\n#     ALT_LOGICAL_SOURCE              Wind_WAVES_Electric-Field-Intensities_Key-Parameters-K0_3min_cdf\n#     MISSION_GROUP                   Wind\n#                                     !___Interplanetary Data near 1 AU\n#\n#  \n# Key Parameter and Survey data (labels K0,K1,K2) are preliminary browse data.\n# Generated by CDAWeb on: Thu Jan 15 22:54:52 2015\n",
			"VariableInfo": "",
			"Cadence": ""
		},
		{
			"Name": "E_transient",
			"ShortDescription": "electric_field>amplitude",
			"LongDescription": "Transient electric field antenna max from Time Domain Sampler. 0 indicates no trigger.",
			"Header": "# ******************************************************* \n#  WARNING: Increase time period selected for listing. \n# ******************************************************* \n# \n#              ************************************\n#              *****    GLOBAL ATTRIBUTES    ******\n#              ************************************\n#\n#     PROJECT                         ISTP>International Solar-Terrestrial Physics\n#     DISCIPLINE                      SPACE PHYSICS>Interplanetary Studies\n#     SOURCE_NAME                     WIND>WIND Interplanetary Plasma Laboratory\n#     DATA_TYPE                       K0>KEY PARAMETER\n#     DESCRIPTOR                      WAV>Radio/Plasma Wave\n#     DATA_VERSION                    1\n#     TITLE                           WIND WAVES CDF format\n#     TEXT                            SSR WAVES: The Radio and Plasma Wave Investigation on the WIND Spacecraft, Vol                         \n#                                      71, pg 231-263,1995.                                                                                  \n#     MODS                            CODED MAY 1996, C. MEETRE\n#     ADID_REF                        NSSD0139\n#     LOGICAL_FILE_ID                 WI_K0_WAV_19920908_V01\n#     LOGICAL_SOURCE                  WI_K0_WAV\n#     LOGICAL_SOURCE_DESCRIPTION      Wind Radio/Plasma Wave, (WAVES) Key Parameters\n#     PI_NAME                         M. L. Kaiser\n#     PI_AFFILIATION                  GSFC\n#     INSTRUMENT_TYPE                 Radio and Plasma Waves (space)\n#     LINK_TEXT                       Wind WAVES\n#     LINK_TITLE                      Home Page (including daily plots, 1-min avg IDL savesets and radio burst lists).\n#     HTTP_LINK                       http://www-lep.gsfc.nasa.gov/waves/\n#     NSSDC_ID                        sphe-00652\n#     ALT_LOGICAL_SOURCE              Wind_WAVES_Electric-Field-Intensities_Key-Parameters-K0_3min_cdf\n#     MISSION_GROUP                   Wind\n#                                     !___Interplanetary Data near 1 AU\n#\n#  \n# Key Parameter and Survey data (labels K0,K1,K2) are preliminary browse data.\n# Generated by CDAWeb on: Thu Jan 15 22:54:52 2015\n",
			"VariableInfo": "",
			"Cadence": ""
		},
		{
			"Name": "Sol_min",
			"ShortDescription": "current>load",
			"LongDescription": "Solar array current minimum for s/c",
			"Header": "# ******************************************************* \n#  WARNING: Increase time period selected for listing. \n# ******************************************************* \n# \n#              ************************************\n#              *****    GLOBAL ATTRIBUTES    ******\n#              ************************************\n#\n#     PROJECT                         ISTP>International Solar-Terrestrial Physics\n#     DISCIPLINE                      SPACE PHYSICS>Interplanetary Studies\n#     SOURCE_NAME                     WIND>WIND Interplanetary Plasma Laboratory\n#     DATA_TYPE                       K0>KEY PARAMETER\n#     DESCRIPTOR                      WAV>Radio/Plasma Wave\n#     DATA_VERSION                    1\n#     TITLE                           WIND WAVES CDF format\n#     TEXT                            SSR WAVES: The Radio and Plasma Wave Investigation on the WIND Spacecraft, Vol                         \n#                                      71, pg 231-263,1995.                                                                                  \n#     MODS                            CODED MAY 1996, C. MEETRE\n#     ADID_REF                        NSSD0139\n#     LOGICAL_FILE_ID                 WI_K0_WAV_19920908_V01\n#     LOGICAL_SOURCE                  WI_K0_WAV\n#     LOGICAL_SOURCE_DESCRIPTION      Wind Radio/Plasma Wave, (WAVES) Key Parameters\n#     PI_NAME                         M. L. Kaiser\n#     PI_AFFILIATION                  GSFC\n#     INSTRUMENT_TYPE                 Radio and Plasma Waves (space)\n#     LINK_TEXT                       Wind WAVES\n#     LINK_TITLE                      Home Page (including daily plots, 1-min avg IDL savesets and radio burst lists).\n#     HTTP_LINK                       http://www-lep.gsfc.nasa.gov/waves/\n#     NSSDC_ID                        sphe-00652\n#     ALT_LOGICAL_SOURCE              Wind_WAVES_Electric-Field-Intensities_Key-Parameters-K0_3min_cdf\n#     MISSION_GROUP                   Wind\n#                                     !___Interplanetary Data near 1 AU\n#\n#  \n# Key Parameter and Survey data (labels K0,K1,K2) are preliminary browse data.\n# Generated by CDAWeb on: Thu Jan 15 22:54:52 2015\n",
			"VariableInfo": "",
			"Cadence": ""
		},
		{
			"Name": "Sol_max",
			"ShortDescription": "current>load",
			"LongDescription": "Solar array current maximum for s/c",
			"Header": "# ******************************************************* \n#  WARNING: Increase time period selected for listing. \n# ******************************************************* \n# \n#              ************************************\n#              *****    GLOBAL ATTRIBUTES    ******\n#              ************************************\n#\n#     PROJECT                         ISTP>International Solar-Terrestrial Physics\n#     DISCIPLINE                      SPACE PHYSICS>Interplanetary Studies\n#     SOURCE_NAME                     WIND>WIND Interplanetary Plasma Laboratory\n#     DATA_TYPE                       K0>KEY PARAMETER\n#     DESCRIPTOR                      WAV>Radio/Plasma Wave\n#     DATA_VERSION                    1\n#     TITLE                           WIND WAVES CDF format\n#     TEXT                            SSR WAVES: The Radio and Plasma Wave Investigation on the WIND Spacecraft, Vol                         \n#                                      71, pg 231-263,1995.                                                                                  \n#     MODS                            CODED MAY 1996, C. MEETRE\n#     ADID_REF                        NSSD0139\n#     LOGICAL_FILE_ID                 WI_K0_WAV_19920908_V01\n#     LOGICAL_SOURCE                  WI_K0_WAV\n#     LOGICAL_SOURCE_DESCRIPTION      Wind Radio/Plasma Wave, (WAVES) Key Parameters\n#     PI_NAME                         M. L. Kaiser\n#     PI_AFFILIATION                  GSFC\n#     INSTRUMENT_TYPE                 Radio and Plasma Waves (space)\n#     LINK_TEXT                       Wind WAVES\n#     LINK_TITLE                      Home Page (including daily plots, 1-min avg IDL savesets and radio burst lists).\n#     HTTP_LINK                       http://www-lep.gsfc.nasa.gov/waves/\n#     NSSDC_ID                        sphe-00652\n#     ALT_LOGICAL_SOURCE              Wind_WAVES_Electric-Field-Intensities_Key-Parameters-K0_3min_cdf\n#     MISSION_GROUP                   Wind\n#                                     !___Interplanetary Data near 1 AU\n#\n#  \n# Key Parameter and Survey data (labels K0,K1,K2) are preliminary browse data.\n# Generated by CDAWeb on: Thu Jan 15 22:54:53 2015\n",
			"VariableInfo": "",
			"Cadence": ""
		},
		{
			"Name": "Moon_pos",
			"ShortDescription": "position>GSE",
			"LongDescription": "Moon Position, Cartesian GSE coordinates",
			"Header": "# ******************************************************* \n#  WARNING: Increase time period selected for listing. \n# ******************************************************* \n# \n#              ************************************\n#              *****    GLOBAL ATTRIBUTES    ******\n#              ************************************\n#\n#     PROJECT                         ISTP>International Solar-Terrestrial Physics\n#     DISCIPLINE                      SPACE PHYSICS>Interplanetary Studies\n#     SOURCE_NAME                     WIND>WIND Interplanetary Plasma Laboratory\n#     DATA_TYPE                       K0>KEY PARAMETER\n#     DESCRIPTOR                      WAV>Radio/Plasma Wave\n#     DATA_VERSION                    1\n#     TITLE                           WIND WAVES CDF format\n#     TEXT                            SSR WAVES: The Radio and Plasma Wave Investigation on the WIND Spacecraft, Vol                         \n#                                      71, pg 231-263,1995.                                                                                  \n#     MODS                            CODED MAY 1996, C. MEETRE\n#     ADID_REF                        NSSD0139\n#     LOGICAL_FILE_ID                 WI_K0_WAV_19920908_V01\n#     LOGICAL_SOURCE                  WI_K0_WAV\n#     LOGICAL_SOURCE_DESCRIPTION      Wind Radio/Plasma Wave, (WAVES) Key Parameters\n#     PI_NAME                         M. L. Kaiser\n#     PI_AFFILIATION                  GSFC\n#     INSTRUMENT_TYPE                 Radio and Plasma Waves (space)\n#     LINK_TEXT                       Wind WAVES\n#     LINK_TITLE                      Home Page (including daily plots, 1-min avg IDL savesets and radio burst lists).\n#     HTTP_LINK                       http://www-lep.gsfc.nasa.gov/waves/\n#     NSSDC_ID                        sphe-00652\n#     ALT_LOGICAL_SOURCE              Wind_WAVES_Electric-Field-Intensities_Key-Parameters-K0_3min_cdf\n#     MISSION_GROUP                   Wind\n#                                     !___Interplanetary Data near 1 AU\n#\n#  \n# Key Parameter and Survey data (labels K0,K1,K2) are preliminary browse data.\n# Generated by CDAWeb on: Thu Jan 15 22:54:53 2015\n",
			"VariableInfo": "",
			"Cadence": ""
		},
		{
			"Name": "Moon_posV",
			"ShortDescription": "position>GSE",
			"LongDescription": "Time axis label: Moon Position, Cartesian GSE coordinates",
			"Header": "# ******************************************************* \n#  WARNING: Increase time period selected for listing. \n# ******************************************************* \n# \n#              ************************************\n#              *****    GLOBAL ATTRIBUTES    ******\n#              ************************************\n#\n#     PROJECT                         ISTP>International Solar-Terrestrial Physics\n#     DISCIPLINE                      SPACE PHYSICS>Interplanetary Studies\n#     SOURCE_NAME                     WIND>WIND Interplanetary Plasma Laboratory\n#     DATA_TYPE                       K0>KEY PARAMETER\n#     DESCRIPTOR                      WAV>Radio/Plasma Wave\n#     DATA_VERSION                    1\n#     TITLE                           WIND WAVES CDF format\n#     TEXT                            SSR WAVES: The Radio and Plasma Wave Investigation on the WIND Spacecraft, Vol                         \n#                                      71, pg 231-263,1995.                                                                                  \n#     MODS                            CODED MAY 1996, C. MEETRE\n#     ADID_REF                        NSSD0139\n#     LOGICAL_FILE_ID                 WI_K0_WAV_19920908_V01\n#     LOGICAL_SOURCE                  WI_K0_WAV\n#     LOGICAL_SOURCE_DESCRIPTION      Wind Radio/Plasma Wave, (WAVES) Key Parameters\n#     PI_NAME                         M. L. Kaiser\n#     PI_AFFILIATION                  GSFC\n#     INSTRUMENT_TYPE                 Radio and Plasma Waves (space)\n#     LINK_TEXT                       Wind WAVES\n#     LINK_TITLE                      Home Page (including daily plots, 1-min avg IDL savesets and radio burst lists).\n#     HTTP_LINK                       http://www-lep.gsfc.nasa.gov/waves/\n#     NSSDC_ID                        sphe-00652\n#     ALT_LOGICAL_SOURCE              Wind_WAVES_Electric-Field-Intensities_Key-Parameters-K0_3min_cdf\n#     MISSION_GROUP                   Wind\n#                                     !___Interplanetary Data near 1 AU\n#\n#  \n# Key Parameter and Survey data (labels K0,K1,K2) are preliminary browse data.\n# Generated by CDAWeb on: Thu Jan 15 22:54:54 2015\n",
			"VariableInfo": "",
			"Cadence": ""
		}
	]
}